anshitsu/__init__.py
anshitsu/__version__.py
anshitsu/cli.py
anshitsu/main.py
anshitsu/process/__init__.py
anshitsu/process/brightness.py
anshitsu/process/color.py
anshitsu/process/color_auto_adjust.py
anshitsu/process/color_stretch.py
anshitsu/process/contrast.py
anshitsu/process/create_alpha_mask.py
anshitsu/process/cyanotype.py
anshitsu/process/grayscale.py
anshitsu/process/invert.py
anshitsu/process/line_drawing.py
anshitsu/process/noise.py
anshitsu/process/output_rgb.py
anshitsu/process/posterize.py
anshitsu/process/processor.py
anshitsu/process/put_alpha_mask.py
anshitsu/process/remove_alpha.py
anshitsu/process/sepia.py
anshitsu/process/sharpness.py
anshitsu-2.1.1.dist-info/LICENSE
anshitsu-2.1.1.dist-info/METADATA
anshitsu-2.1.1.dist-info/WHEEL
anshitsu-2.1.1.dist-info/entry_points.txt
anshitsu-2.1.1.dist-info/RECORD
