Metadata-Version: 2.1
Name: anshitsu
Version: 2.1.1
Summary: A tiny digital photographic utility.
Home-page: https://github.com/huideyeren
License: MIT
Author: Iosif Takakura
Author-email: iosif@huideyeren.info
Requires-Python: >=3.11,<4.0
Classifier: License :: OSI Approved :: MIT License
Classifier: Programming Language :: Python :: 3
Classifier: Programming Language :: Python :: 3.11
Classifier: Programming Language :: Python :: 3.12
Requires-Dist: Pillow
Requires-Dist: colorcorrect
Requires-Dist: fire
Requires-Dist: numpy
Project-URL: Documentation, https://github.com/huideyeren/anshitsu
Project-URL: Repository, https://github.com/huideyeren/anshitsu
